declared.py
setup.py
declared.egg-info/PKG-INFO
declared.egg-info/SOURCES.txt
declared.egg-info/dependency_links.txt
declared.egg-info/top_level.txt