Metadata-Version: 1.1
Name: declared
Version: 0.2
Summary: declared
Home-page: https://github.com/abetkin/declared
Author: abetkin
Author-email: abvit89@gmail.com
License: MIT
Platform: UNKNOWN
Classifier: Development Status :: 3 - Alpha
Classifier: Intended Audience :: Developers
Classifier: Programming Language :: Python :: 3.4
